{
  "meta": {
    "version": "prices-1.0.0",
    "schemaVersion": 1,
    "generated_at": "2026-06-27T06:30:11.158Z",
    "epoch": 191,
    "source": "network-and-prices (consolidated)",
    "token_count": 27
  },
  "prices": {
    "LUNA": {
      "price_usd": 0.050561,
      "type": "token",
      "source": "astroport",
      "change_24h_pct": 5.498389699921864,
      "change_7d_pct": -1.4539926325842414
    },
    "USDC": {
      "price_usd": 0.999793,
      "type": "token",
      "source": "astroport",
      "change_24h_pct": 0.011303617157493373,
      "change_7d_pct": -0.002100390672658888
    },
    "USDT": {
      "price_usd": 0.998586,
      "type": "token",
      "source": "astroport",
      "change_24h_pct": 0.006910247897630761,
      "change_7d_pct": -0.04754464442111175
    },
    "WBTC": {
      "price_usd": 60110,
      "type": "token",
      "source": "astroport",
      "change_24h_pct": 0.7475194422097077,
      "change_7d_pct": -4.992966539695585
    },
    "PAXG": {
      "price_usd": 4072.63,
      "type": "token",
      "source": "astroport",
      "change_24h_pct": 1.5750172092141648,
      "change_7d_pct": -1.8960142989974331
    },
    "EURE": {
      "price_usd": 1.14,
      "type": "token",
      "source": "astroport",
      "change_24h_pct": 0,
      "change_7d_pct": -0.8695652173913052
    },
    "INJ": {
      "price_usd": 4.839136283910956,
      "type": "token",
      "source": "coingecko",
      "change_24h_pct": null,
      "change_7d_pct": null
    },
    "ATOM": {
      "price_usd": 1.59,
      "type": "token",
      "source": "astroport",
      "change_24h_pct": -1.2422360248447215,
      "change_7d_pct": -12.154696132596683
    },
    "ETH": {
      "price_usd": 1576.24,
      "type": "token",
      "source": "astroport",
      "change_24h_pct": 0.7201416001584683,
      "change_7d_pct": -7.858324516125265
    },
    "WETH": {
      "price_usd": 1576.771913991292,
      "type": "token",
      "source": "coingecko",
      "change_24h_pct": null,
      "change_7d_pct": null
    },
    "WSTETH": {
      "price_usd": 1949.98,
      "type": "token",
      "source": "astroport",
      "change_24h_pct": 0.3540733878853435,
      "change_7d_pct": -7.804543627810225
    },
    "BNB": {
      "price_usd": 563.48,
      "type": "token",
      "source": "astroport",
      "change_24h_pct": 0.6699658764046952,
      "change_7d_pct": -3.075546993257189
    },
    "WBNB": {
      "price_usd": 563.443554196733,
      "type": "token",
      "source": "coingecko",
      "change_24h_pct": null,
      "change_7d_pct": null
    },
    "OSMO": {
      "price_usd": 0.03850431219075459,
      "type": "token",
      "source": "coingecko",
      "change_24h_pct": null,
      "change_7d_pct": null
    },
    "STLUNA": {
      "price_usd": 0.08672680415484058,
      "type": "token",
      "source": "coingecko",
      "change_24h_pct": null,
      "change_7d_pct": null
    },
    "STATOM": {
      "price_usd": 3.0632928565922,
      "type": "token",
      "source": "coingecko",
      "change_24h_pct": null,
      "change_7d_pct": null
    },
    "SOLID": {
      "price_usd": 1.008140840415109,
      "type": "token",
      "source": "astroport",
      "change_24h_pct": 0.813507652570715,
      "change_7d_pct": 0.6697232162524299
    },
    "SWTH": {
      "price_usd": 0.000462103583280351,
      "type": "token",
      "source": "coingecko",
      "change_24h_pct": null,
      "change_7d_pct": null
    },
    "ROAR": {
      "price_usd": 2.05686371252e-7,
      "type": "token",
      "source": "astroport",
      "change_24h_pct": 4.659949223873937,
      "change_7d_pct": -5.372551673603415
    },
    "CAPA": {
      "price_usd": 0.001167000967669949,
      "type": "token",
      "source": "astroport",
      "change_24h_pct": 5.870028476051706,
      "change_7d_pct": 2.2717093106184345
    },
    "ASTRO": {
      "price_usd": 0.000584242756819218,
      "type": "token",
      "source": "coingecko (astroport flagged stale)",
      "change_24h_pct": 13.277276314267498,
      "change_7d_pct": -10.625663502176355
    },
    "xASTRO": {
      "price_usd": 0.000530210265990899,
      "type": "token",
      "source": "astroport-direct",
      "change_24h_pct": null,
      "change_7d_pct": null
    },
    "ampLUNA": {
      "price_usd": 0.11049033822677191,
      "type": "token",
      "source": "calculated-eris",
      "change_24h_pct": null,
      "change_7d_pct": null
    },
    "arbLUNA": {
      "price_usd": 0.1501489796324078,
      "type": "token",
      "source": "calculated-eris",
      "change_24h_pct": null,
      "change_7d_pct": null
    },
    "bLUNA": {
      "price_usd": 0.08948682958254929,
      "type": "token",
      "source": "calculated-eris",
      "change_24h_pct": null,
      "change_7d_pct": null
    },
    "ampCAPA": {
      "price_usd": 0.00129016361536606,
      "type": "token",
      "source": "calculated-eris",
      "change_24h_pct": null,
      "change_7d_pct": null
    },
    "ampROAR": {
      "price_usd": 2.4163265998105964e-7,
      "type": "token",
      "source": "calculated-eris",
      "change_24h_pct": null,
      "change_7d_pct": null
    }
  },
  "ratios": {
    "ampLUNA": {
      "ratio": 2.1852878350264415,
      "hub": "terra10788fkzah89xrdm27zkj5yvhj9x3494lxawzm5qq3vvxcqz2yzaqyd3enk",
      "base_token": "LUNA",
      "source": "eris-hub-chain"
    },
    "arbLUNA": {
      "ratio": 2.969660007365515,
      "hub": "terra1r9gls56glvuc4jedsvc3uwh6vj95mqm9efc7hnweqxa2nlme5cyqxygy5m",
      "base_token": "LUNA",
      "source": "eris-hub-chain"
    },
    "ampROAR": {
      "ratio": 1.174762618010405,
      "hub": "terra1vklefn7n6cchn0u962w3gaszr4vf52wjvd4y95t2sydwpmpdtszsqvk9wy",
      "base_token": "ROAR",
      "source": "eris-hub-chain"
    },
    "ampCAPA": {
      "ratio": 1.1055377425624755,
      "hub": "terra186rpfczl7l2kugdsqqedegl4es4hp624phfc7ddy8my02a4e8lgq5rlx7y",
      "base_token": "CAPA",
      "source": "eris-hub-chain"
    },
    "bLUNA": {
      "ratio": 1.7698785542720532,
      "hub": "terra1l2nd99yze5fszmhl5svyh5fky9wm4nz4etlgnztfu4e8809gd52q04n3ea",
      "base_token": "LUNA",
      "source": "eris-hub-chain"
    },
    "xASTRO": {
      "ratio": 1.3091595836923766,
      "base_token": "ASTRO",
      "source": "astroport-trpc"
    }
  }
}