{
  "meta": {
    "version": "prices-1.0.0",
    "schemaVersion": 1,
    "generated_at": "2026-07-02T08:00:10.388Z",
    "epoch": 192,
    "source": "network-and-prices (consolidated)",
    "token_count": 27
  },
  "prices": {
    "LUNA": {
      "price_usd": 0.04660925,
      "type": "token",
      "source": "astroport",
      "change_24h_pct": 1.3269676683291616,
      "change_7d_pct": -3.3096392153039256
    },
    "USDC": {
      "price_usd": 0.999649,
      "type": "token",
      "source": "astroport",
      "change_24h_pct": 0.002600980569671815,
      "change_7d_pct": -0.013202891433225974
    },
    "USDT": {
      "price_usd": 0.998701,
      "type": "token",
      "source": "astroport",
      "change_24h_pct": 0.02674187778059503,
      "change_7d_pct": 0.01962934587207615
    },
    "WBTC": {
      "price_usd": 60021,
      "type": "token",
      "source": "astroport",
      "change_24h_pct": 2.6508867643789227,
      "change_7d_pct": -1.359124375493032
    },
    "PAXG": {
      "price_usd": 4055.56,
      "type": "token",
      "source": "astroport",
      "change_24h_pct": 1.4128320155236482,
      "change_7d_pct": 1.2214784531600216
    },
    "EURE": {
      "price_usd": 1.14,
      "type": "token",
      "source": "astroport",
      "change_24h_pct": 0,
      "change_7d_pct": 0
    },
    "INJ": {
      "price_usd": 4.563205592939623,
      "type": "token",
      "source": "coingecko",
      "change_24h_pct": null,
      "change_7d_pct": null
    },
    "ATOM": {
      "price_usd": 1.54,
      "type": "token",
      "source": "astroport",
      "change_24h_pct": 1.986754966887419,
      "change_7d_pct": -6.66666666666666
    },
    "ETH": {
      "price_usd": 1614.86,
      "type": "token",
      "source": "astroport",
      "change_24h_pct": 2.8782936649508075,
      "change_7d_pct": -0.3037449530183156
    },
    "WETH": {
      "price_usd": 1614.784686333143,
      "type": "token",
      "source": "coingecko",
      "change_24h_pct": null,
      "change_7d_pct": null
    },
    "WSTETH": {
      "price_usd": 1997.56,
      "type": "token",
      "source": "astroport",
      "change_24h_pct": 2.6885866156709106,
      "change_7d_pct": -0.3387631900616142
    },
    "BNB": {
      "price_usd": 548.5,
      "type": "token",
      "source": "astroport",
      "change_24h_pct": 0.48179969589828997,
      "change_7d_pct": -2.7240804455006584
    },
    "WBNB": {
      "price_usd": 548.6009166810666,
      "type": "token",
      "source": "coingecko",
      "change_24h_pct": null,
      "change_7d_pct": null
    },
    "OSMO": {
      "price_usd": 0.03570598574294086,
      "type": "token",
      "source": "coingecko",
      "change_24h_pct": null,
      "change_7d_pct": null
    },
    "STLUNA": {
      "price_usd": 0.08672680415484058,
      "type": "token",
      "source": "coingecko",
      "change_24h_pct": null,
      "change_7d_pct": null
    },
    "STATOM": {
      "price_usd": 3.1247135883921335,
      "type": "token",
      "source": "coingecko",
      "change_24h_pct": null,
      "change_7d_pct": null
    },
    "SOLID": {
      "price_usd": 1.0083049415693914,
      "type": "token",
      "source": "astroport",
      "change_24h_pct": 0.4588678812588381,
      "change_7d_pct": 0.7563491568564922
    },
    "SWTH": {
      "price_usd": 0.000460387336683591,
      "type": "token",
      "source": "coingecko",
      "change_24h_pct": null,
      "change_7d_pct": null
    },
    "ROAR": {
      "price_usd": 1.93049823752e-7,
      "type": "token",
      "source": "astroport",
      "change_24h_pct": 2.02160170947609,
      "change_7d_pct": -1.9220808774226685
    },
    "CAPA": {
      "price_usd": 0.001035369990523475,
      "type": "token",
      "source": "astroport",
      "change_24h_pct": -2.728184220246277,
      "change_7d_pct": -5.797754052455884
    },
    "ASTRO": {
      "price_usd": 0.00026109791928292,
      "type": "token",
      "source": "astroport",
      "change_24h_pct": 0,
      "change_7d_pct": -12.176560420894509
    },
    "xASTRO": {
      "price_usd": 0.000343091745279138,
      "type": "token",
      "source": "astroport-direct",
      "change_24h_pct": null,
      "change_7d_pct": null
    },
    "ampLUNA": {
      "price_usd": 0.10222083562117755,
      "type": "token",
      "source": "calculated-eris",
      "change_24h_pct": null,
      "change_7d_pct": null
    },
    "arbLUNA": {
      "price_usd": 0.13841362569909416,
      "type": "token",
      "source": "calculated-eris",
      "change_24h_pct": null,
      "change_7d_pct": null
    },
    "bLUNA": {
      "price_usd": 0.08249271200580391,
      "type": "token",
      "source": "calculated-eris",
      "change_24h_pct": null,
      "change_7d_pct": null
    },
    "ampCAPA": {
      "price_usd": 0.0011446406020403452,
      "type": "token",
      "source": "calculated-eris",
      "change_24h_pct": null,
      "change_7d_pct": null
    },
    "ampROAR": {
      "price_usd": 2.2702260245967898e-7,
      "type": "token",
      "source": "calculated-eris",
      "change_24h_pct": null,
      "change_7d_pct": null
    }
  },
  "ratios": {
    "ampLUNA": {
      "ratio": 2.193144829002345,
      "hub": "terra10788fkzah89xrdm27zkj5yvhj9x3494lxawzm5qq3vvxcqz2yzaqyd3enk",
      "base_token": "LUNA",
      "source": "eris-hub-chain"
    },
    "arbLUNA": {
      "ratio": 2.9696600073825294,
      "hub": "terra1r9gls56glvuc4jedsvc3uwh6vj95mqm9efc7hnweqxa2nlme5cyqxygy5m",
      "base_token": "LUNA",
      "source": "eris-hub-chain"
    },
    "ampROAR": {
      "ratio": 1.1759793303480135,
      "hub": "terra1vklefn7n6cchn0u962w3gaszr4vf52wjvd4y95t2sydwpmpdtszsqvk9wy",
      "base_token": "ROAR",
      "source": "eris-hub-chain"
    },
    "ampCAPA": {
      "ratio": 1.1055377425625634,
      "hub": "terra186rpfczl7l2kugdsqqedegl4es4hp624phfc7ddy8my02a4e8lgq5rlx7y",
      "base_token": "CAPA",
      "source": "eris-hub-chain"
    },
    "bLUNA": {
      "ratio": 1.769878554274182,
      "hub": "terra1l2nd99yze5fszmhl5svyh5fky9wm4nz4etlgnztfu4e8809gd52q04n3ea",
      "base_token": "LUNA",
      "source": "eris-hub-chain"
    },
    "xASTRO": {
      "ratio": 1.3140263970588228,
      "base_token": "ASTRO",
      "source": "astroport-trpc"
    }
  }
}