{
  "meta": {
    "version": "prices-1.0.0",
    "schemaVersion": 1,
    "generated_at": "2026-07-04T04:45:07.403Z",
    "epoch": 192,
    "source": "network-and-prices (consolidated)",
    "token_count": 27
  },
  "prices": {
    "LUNA": {
      "price_usd": 0.05069,
      "type": "token",
      "source": "astroport",
      "change_24h_pct": 5.766452066556288,
      "change_7d_pct": 1.5218056581432902
    },
    "USDC": {
      "price_usd": 0.999885,
      "type": "token",
      "source": "astroport",
      "change_24h_pct": 0.006601194816262794,
      "change_7d_pct": 0.01180275004076575
    },
    "USDT": {
      "price_usd": 0.999097,
      "type": "token",
      "source": "astroport",
      "change_24h_pct": 0.029435233975069808,
      "change_7d_pct": 0.03885015555082161
    },
    "WBTC": {
      "price_usd": 62567,
      "type": "token",
      "source": "astroport",
      "change_24h_pct": 1.8409401653753499,
      "change_7d_pct": 4.408844388819357
    },
    "PAXG": {
      "price_usd": 4161.34,
      "type": "token",
      "source": "astroport",
      "change_24h_pct": 0.9997208839484123,
      "change_7d_pct": 2.0832004553014674
    },
    "EURE": {
      "price_usd": 1.14,
      "type": "token",
      "source": "astroport",
      "change_24h_pct": 0,
      "change_7d_pct": 0
    },
    "INJ": {
      "price_usd": 4.902400415035377,
      "type": "token",
      "source": "coingecko",
      "change_24h_pct": null,
      "change_7d_pct": null
    },
    "ATOM": {
      "price_usd": 1.59,
      "type": "token",
      "source": "astroport",
      "change_24h_pct": 1.9230769230769247,
      "change_7d_pct": -0.6250000000000006
    },
    "ETH": {
      "price_usd": 1756.05,
      "type": "token",
      "source": "astroport",
      "change_24h_pct": 3.402285855605997,
      "change_7d_pct": 11.400459291777157
    },
    "WETH": {
      "price_usd": 1756.0468144889069,
      "type": "token",
      "source": "coingecko",
      "change_24h_pct": null,
      "change_7d_pct": null
    },
    "WSTETH": {
      "price_usd": 2172.1,
      "type": "token",
      "source": "astroport",
      "change_24h_pct": 3.4180668567973282,
      "change_7d_pct": 11.218637992831537
    },
    "BNB": {
      "price_usd": 572.32,
      "type": "token",
      "source": "astroport",
      "change_24h_pct": 2.568146382551666,
      "change_7d_pct": 0.9970529585120248
    },
    "WBNB": {
      "price_usd": 572.3179222296403,
      "type": "token",
      "source": "coingecko",
      "change_24h_pct": null,
      "change_7d_pct": null
    },
    "OSMO": {
      "price_usd": 0.03786432622625507,
      "type": "token",
      "source": "coingecko",
      "change_24h_pct": null,
      "change_7d_pct": null
    },
    "STLUNA": {
      "price_usd": 0.08672680415484058,
      "type": "token",
      "source": "coingecko",
      "change_24h_pct": null,
      "change_7d_pct": null
    },
    "STATOM": {
      "price_usd": 3.18588127055565,
      "type": "token",
      "source": "coingecko",
      "change_24h_pct": null,
      "change_7d_pct": null
    },
    "SOLID": {
      "price_usd": 1.0052425450278182,
      "type": "token",
      "source": "astroport",
      "change_24h_pct": -0.2716922730155662,
      "change_7d_pct": -0.12829972486116772
    },
    "SWTH": {
      "price_usd": 0.000302166975018104,
      "type": "token",
      "source": "coingecko",
      "change_24h_pct": null,
      "change_7d_pct": null
    },
    "ROAR": {
      "price_usd": 2.11388291253e-7,
      "type": "token",
      "source": "astroport",
      "change_24h_pct": 6.4891773019077394,
      "change_7d_pct": 4.268621156696015
    },
    "CAPA": {
      "price_usd": 0.001143225423564467,
      "type": "token",
      "source": "astroport",
      "change_24h_pct": 7.288231451332401,
      "change_7d_pct": -0.8736162625439801
    },
    "ASTRO": {
      "price_usd": 0.000420999596434456,
      "type": "token",
      "source": "coingecko (astroport flagged stale)",
      "change_24h_pct": 15.435982948679225,
      "change_7d_pct": -26.276608449140916
    },
    "xASTRO": {
      "price_usd": 0.000398959016998403,
      "type": "token",
      "source": "astroport-direct",
      "change_24h_pct": null,
      "change_7d_pct": null
    },
    "ampLUNA": {
      "price_usd": 0.11134235474155467,
      "type": "token",
      "source": "calculated-eris",
      "change_24h_pct": null,
      "change_7d_pct": null
    },
    "arbLUNA": {
      "price_usd": 0.15084902025091515,
      "type": "token",
      "source": "calculated-eris",
      "change_24h_pct": null,
      "change_7d_pct": null
    },
    "bLUNA": {
      "price_usd": 0.08971514391619426,
      "type": "token",
      "source": "calculated-eris",
      "change_24h_pct": null,
      "change_7d_pct": null
    },
    "ampCAPA": {
      "price_usd": 0.0012638788540076172,
      "type": "token",
      "source": "calculated-eris",
      "change_24h_pct": null,
      "change_7d_pct": null
    },
    "ampROAR": {
      "price_usd": 2.4869300808471933e-7,
      "type": "token",
      "source": "calculated-eris",
      "change_24h_pct": null,
      "change_7d_pct": null
    }
  },
  "ratios": {
    "ampLUNA": {
      "ratio": 2.196534913031262,
      "hub": "terra10788fkzah89xrdm27zkj5yvhj9x3494lxawzm5qq3vvxcqz2yzaqyd3enk",
      "base_token": "LUNA",
      "source": "eris-hub-chain"
    },
    "arbLUNA": {
      "ratio": 2.9759128082642565,
      "hub": "terra1r9gls56glvuc4jedsvc3uwh6vj95mqm9efc7hnweqxa2nlme5cyqxygy5m",
      "base_token": "LUNA",
      "source": "eris-hub-chain"
    },
    "ampROAR": {
      "ratio": 1.1764748492482546,
      "hub": "terra1vklefn7n6cchn0u962w3gaszr4vf52wjvd4y95t2sydwpmpdtszsqvk9wy",
      "base_token": "ROAR",
      "source": "eris-hub-chain"
    },
    "ampCAPA": {
      "ratio": 1.105537742562586,
      "hub": "terra186rpfczl7l2kugdsqqedegl4es4hp624phfc7ddy8my02a4e8lgq5rlx7y",
      "base_token": "CAPA",
      "source": "eris-hub-chain"
    },
    "bLUNA": {
      "ratio": 1.7698785542748916,
      "hub": "terra1l2nd99yze5fszmhl5svyh5fky9wm4nz4etlgnztfu4e8809gd52q04n3ea",
      "base_token": "LUNA",
      "source": "eris-hub-chain"
    },
    "xASTRO": {
      "ratio": 1.3145365741627864,
      "base_token": "ASTRO",
      "source": "astroport-trpc"
    }
  }
}