{
  "meta": {
    "version": "prices-1.0.0",
    "schemaVersion": 1,
    "generated_at": "2026-07-15T02:30:43.651Z",
    "epoch": 194,
    "source": "network-and-prices (consolidated)",
    "token_count": 20
  },
  "prices": {
    "LUNA": {
      "price_usd": 0.04765941,
      "type": "token",
      "source": "astroport",
      "change_24h_pct": 2.2988769736672587,
      "change_7d_pct": -5.679095173068927
    },
    "USDC": {
      "price_usd": 0.99985,
      "type": "token",
      "source": "astroport",
      "change_24h_pct": -0.0008001136161342911,
      "change_7d_pct": -0.004500472549613883
    },
    "USDT": {
      "price_usd": 0.99929,
      "type": "token",
      "source": "astroport",
      "change_24h_pct": 0.052665094056256176,
      "change_7d_pct": 0.0035026094440365318
    },
    "WBTC": {
      "price_usd": 64820,
      "type": "token",
      "source": "astroport",
      "change_24h_pct": 4.131859658141627,
      "change_7d_pct": 2.205893946799956
    },
    "PAXG": {
      "price_usd": 4041.23,
      "type": "token",
      "source": "astroport",
      "change_24h_pct": 1.215975234679468,
      "change_7d_pct": -1.2455402961732027
    },
    "EURE": {
      "price_usd": 1.14,
      "type": "token",
      "source": "astroport",
      "change_24h_pct": 0.8849557522123902,
      "change_7d_pct": 0
    },
    "ATOM": {
      "price_usd": 1.56,
      "type": "token",
      "source": "astroport",
      "change_24h_pct": 1.2987012987012998,
      "change_7d_pct": -0.6369426751592362
    },
    "ETH": {
      "price_usd": 1875.04,
      "type": "token",
      "source": "astroport",
      "change_24h_pct": 5.681901444570317,
      "change_7d_pct": 6.028511165270884
    },
    "WSTETH": {
      "price_usd": 2323.74,
      "type": "token",
      "source": "astroport",
      "change_24h_pct": 5.8000774011428,
      "change_7d_pct": 6.07052379322149
    },
    "BNB": {
      "price_usd": 580.44,
      "type": "token",
      "source": "astroport",
      "change_24h_pct": 2.417334227335294,
      "change_7d_pct": 0.6781954104730166
    },
    "SOLID": {
      "price_usd": 1.0244797881717893,
      "type": "token",
      "source": "astroport",
      "change_24h_pct": 0.7151213807116377,
      "change_7d_pct": 0.5270987651528293
    },
    "ROAR": {
      "price_usd": 2.01099801628e-7,
      "type": "token",
      "source": "astroport",
      "change_24h_pct": 2.7400660236989887,
      "change_7d_pct": -4.728486209178804
    },
    "CAPA": {
      "price_usd": 0.001092493275005083,
      "type": "token",
      "source": "astroport",
      "change_24h_pct": 2.785942293910449,
      "change_7d_pct": -4.013540600417687
    },
    "ASTRO": {
      "price_usd": 0.000282929983559831,
      "type": "token",
      "source": "astroport",
      "change_24h_pct": 2.5818965227557307,
      "change_7d_pct": -10.284890804415598
    },
    "xASTRO": {
      "price_usd": 0.000373697121522271,
      "type": "token",
      "source": "astroport-direct",
      "change_24h_pct": null,
      "change_7d_pct": null
    },
    "ampLUNA": {
      "price_usd": 0.10561974987651214,
      "type": "token",
      "source": "calculated-eris",
      "change_24h_pct": null,
      "change_7d_pct": null
    },
    "arbLUNA": {
      "price_usd": 0.14225878480798693,
      "type": "token",
      "source": "calculated-eris",
      "change_24h_pct": null,
      "change_7d_pct": null
    },
    "bLUNA": {
      "price_usd": 0.08435136766886711,
      "type": "token",
      "source": "calculated-eris",
      "change_24h_pct": null,
      "change_7d_pct": null
    },
    "ampCAPA": {
      "price_usd": 0.0012077925490141252,
      "type": "token",
      "source": "calculated-eris",
      "change_24h_pct": null,
      "change_7d_pct": null
    },
    "ampROAR": {
      "price_usd": 2.371296655981326e-7,
      "type": "token",
      "source": "calculated-eris",
      "change_24h_pct": null,
      "change_7d_pct": null
    }
  },
  "ratios": {
    "ampLUNA": {
      "ratio": 2.2161363280936994,
      "hub": "terra10788fkzah89xrdm27zkj5yvhj9x3494lxawzm5qq3vvxcqz2yzaqyd3enk",
      "base_token": "LUNA",
      "source": "eris-hub-chain"
    },
    "arbLUNA": {
      "ratio": 2.984904446110158,
      "hub": "terra1r9gls56glvuc4jedsvc3uwh6vj95mqm9efc7hnweqxa2nlme5cyqxygy5m",
      "base_token": "LUNA",
      "source": "eris-hub-chain"
    },
    "ampROAR": {
      "ratio": 1.179164095033677,
      "hub": "terra1vklefn7n6cchn0u962w3gaszr4vf52wjvd4y95t2sydwpmpdtszsqvk9wy",
      "base_token": "ROAR",
      "source": "eris-hub-chain"
    },
    "ampCAPA": {
      "ratio": 1.1055377425627684,
      "hub": "terra186rpfczl7l2kugdsqqedegl4es4hp624phfc7ddy8my02a4e8lgq5rlx7y",
      "base_token": "CAPA",
      "source": "eris-hub-chain"
    },
    "bLUNA": {
      "ratio": 1.7698785542848121,
      "hub": "terra1l2nd99yze5fszmhl5svyh5fky9wm4nz4etlgnztfu4e8809gd52q04n3ea",
      "base_token": "LUNA",
      "source": "eris-hub-chain"
    },
    "xASTRO": {
      "ratio": 1.320811307519995,
      "base_token": "ASTRO",
      "source": "astroport-trpc"
    }
  }
}