{
  "meta": {
    "version": "prices-1.0.0",
    "schemaVersion": 1,
    "generated_at": "2026-07-14T11:00:16.136Z",
    "epoch": 194,
    "source": "network-and-prices (consolidated)",
    "token_count": 27
  },
  "prices": {
    "LUNA": {
      "price_usd": 0.04678648,
      "type": "token",
      "source": "astroport",
      "change_24h_pct": -1.6552132649121105,
      "change_7d_pct": -5.766292086854607
    },
    "USDC": {
      "price_usd": 0.999872,
      "type": "token",
      "source": "astroport",
      "change_24h_pct": 0.0066012806484468485,
      "change_7d_pct": -0.007000406023550816
    },
    "USDT": {
      "price_usd": 0.998847,
      "type": "token",
      "source": "astroport",
      "change_24h_pct": -0.05183291390031744,
      "change_7d_pct": -0.05493317964049393
    },
    "WBTC": {
      "price_usd": 62647,
      "type": "token",
      "source": "astroport",
      "change_24h_pct": -1.6823867292330388,
      "change_7d_pct": -2.1217092414655103
    },
    "PAXG": {
      "price_usd": 4008.93,
      "type": "token",
      "source": "astroport",
      "change_24h_pct": -1.630040045541996,
      "change_7d_pct": -3.4616199659015487
    },
    "EURE": {
      "price_usd": 1.13,
      "type": "token",
      "source": "astroport",
      "change_24h_pct": -0.8771929824561412,
      "change_7d_pct": -0.8771929824561412
    },
    "INJ": {
      "price_usd": 5.006825365016674,
      "type": "token",
      "source": "coingecko",
      "change_24h_pct": null,
      "change_7d_pct": null
    },
    "ATOM": {
      "price_usd": 1.52,
      "type": "token",
      "source": "astroport",
      "change_24h_pct": -3.184713375796181,
      "change_7d_pct": -5.000000000000004
    },
    "ETH": {
      "price_usd": 1788.51,
      "type": "token",
      "source": "astroport",
      "change_24h_pct": -0.9448539796296984,
      "change_7d_pct": -0.5377659633629599
    },
    "WETH": {
      "price_usd": 1789.1678983976776,
      "type": "token",
      "source": "coingecko",
      "change_24h_pct": null,
      "change_7d_pct": null
    },
    "WSTETH": {
      "price_usd": 2213.25,
      "type": "token",
      "source": "astroport",
      "change_24h_pct": -1.1505084836601989,
      "change_7d_pct": -0.5915325949281839
    },
    "BNB": {
      "price_usd": 569.48,
      "type": "token",
      "source": "astroport",
      "change_24h_pct": -0.7770847126877436,
      "change_7d_pct": -2.7377841539854098
    },
    "WBNB": {
      "price_usd": 569.476940558189,
      "type": "token",
      "source": "coingecko",
      "change_24h_pct": null,
      "change_7d_pct": null
    },
    "OSMO": {
      "price_usd": 0.0326428444822457,
      "type": "token",
      "source": "coingecko",
      "change_24h_pct": null,
      "change_7d_pct": null
    },
    "STLUNA": {
      "price_usd": 0.08618530248070035,
      "type": "token",
      "source": "coingecko",
      "change_24h_pct": null,
      "change_7d_pct": null
    },
    "STATOM": {
      "price_usd": 2.923436174717345,
      "type": "token",
      "source": "coingecko",
      "change_24h_pct": null,
      "change_7d_pct": null
    },
    "SOLID": {
      "price_usd": 1.0244791799179631,
      "type": "token",
      "source": "astroport",
      "change_24h_pct": 0.710584377618352,
      "change_7d_pct": -0.7346691576943459
    },
    "SWTH": {
      "price_usd": 0.000246847005388715,
      "type": "token",
      "source": "coingecko",
      "change_24h_pct": null,
      "change_7d_pct": null
    },
    "ROAR": {
      "price_usd": 1.97628415824e-7,
      "type": "token",
      "source": "astroport",
      "change_24h_pct": -1.6439619428023216,
      "change_7d_pct": -4.984897870988555
    },
    "CAPA": {
      "price_usd": 0.001070826488952458,
      "type": "token",
      "source": "astroport",
      "change_24h_pct": -2.067497337693671,
      "change_7d_pct": -4.0090984042767674
    },
    "ASTRO": {
      "price_usd": 0.000274760569925821,
      "type": "token",
      "source": "astroport",
      "change_24h_pct": 0.3076264897588052,
      "change_7d_pct": -14.030012292925525
    },
    "xASTRO": {
      "price_usd": 0.00036269040953495,
      "type": "token",
      "source": "astroport-direct",
      "change_24h_pct": null,
      "change_7d_pct": null
    },
    "ampLUNA": {
      "price_usd": 0.103634525027739,
      "type": "token",
      "source": "calculated-eris",
      "change_24h_pct": null,
      "change_7d_pct": null
    },
    "arbLUNA": {
      "price_usd": 0.13961093463388513,
      "type": "token",
      "source": "calculated-eris",
      "change_24h_pct": null,
      "change_7d_pct": null
    },
    "bLUNA": {
      "price_usd": 0.08280638758247051,
      "type": "token",
      "source": "calculated-eris",
      "change_24h_pct": null,
      "change_7d_pct": null
    },
    "ampCAPA": {
      "price_usd": 0.0011838390992729082,
      "type": "token",
      "source": "calculated-eris",
      "change_24h_pct": null,
      "change_7d_pct": null
    },
    "ampROAR": {
      "price_usd": 2.330363320980462e-7,
      "type": "token",
      "source": "calculated-eris",
      "change_24h_pct": null,
      "change_7d_pct": null
    }
  },
  "ratios": {
    "ampLUNA": {
      "ratio": 2.215052832094635,
      "hub": "terra10788fkzah89xrdm27zkj5yvhj9x3494lxawzm5qq3vvxcqz2yzaqyd3enk",
      "base_token": "LUNA",
      "source": "eris-hub-chain"
    },
    "arbLUNA": {
      "ratio": 2.984001673857173,
      "hub": "terra1r9gls56glvuc4jedsvc3uwh6vj95mqm9efc7hnweqxa2nlme5cyqxygy5m",
      "base_token": "LUNA",
      "source": "eris-hub-chain"
    },
    "ampROAR": {
      "ratio": 1.179164095033677,
      "hub": "terra1vklefn7n6cchn0u962w3gaszr4vf52wjvd4y95t2sydwpmpdtszsqvk9wy",
      "base_token": "ROAR",
      "source": "eris-hub-chain"
    },
    "ampCAPA": {
      "ratio": 1.1055377425627615,
      "hub": "terra186rpfczl7l2kugdsqqedegl4es4hp624phfc7ddy8my02a4e8lgq5rlx7y",
      "base_token": "CAPA",
      "source": "eris-hub-chain"
    },
    "bLUNA": {
      "ratio": 1.7698785542847104,
      "hub": "terra1l2nd99yze5fszmhl5svyh5fky9wm4nz4etlgnztfu4e8809gd52q04n3ea",
      "base_token": "LUNA",
      "source": "eris-hub-chain"
    },
    "xASTRO": {
      "ratio": 1.3208113075199899,
      "base_token": "ASTRO",
      "source": "astroport-trpc"
    }
  }
}