{
  "meta": {
    "version": "prices-1.0.0",
    "schemaVersion": 1,
    "generated_at": "2026-07-11T00:15:20.965Z",
    "epoch": 193,
    "source": "network-and-prices (consolidated)",
    "token_count": 27
  },
  "prices": {
    "LUNA": {
      "price_usd": 0.04879185,
      "type": "token",
      "source": "astroport",
      "change_24h_pct": 2.458576616853261,
      "change_7d_pct": 1.8058959215546317
    },
    "USDC": {
      "price_usd": 0.999911,
      "type": "token",
      "source": "astroport",
      "change_24h_pct": 0.0033004026491181664,
      "change_7d_pct": 0.009201665501453862
    },
    "USDT": {
      "price_usd": 0.999339,
      "type": "token",
      "source": "astroport",
      "change_24h_pct": 0.010708223915964283,
      "change_7d_pct": 0.05366423609059854
    },
    "WBTC": {
      "price_usd": 64112,
      "type": "token",
      "source": "astroport",
      "change_24h_pct": 3.1701586688552026,
      "change_7d_pct": 4.355752327625496
    },
    "PAXG": {
      "price_usd": 4111.41,
      "type": "token",
      "source": "astroport",
      "change_24h_pct": 1.0315941053169613,
      "change_7d_pct": -0.21212819921604267
    },
    "EURE": {
      "price_usd": 1.14,
      "type": "token",
      "source": "astroport",
      "change_24h_pct": 0,
      "change_7d_pct": 0
    },
    "INJ": {
      "price_usd": 4.994760717075632,
      "type": "token",
      "source": "coingecko",
      "change_24h_pct": null,
      "change_7d_pct": null
    },
    "ATOM": {
      "price_usd": 1.58,
      "type": "token",
      "source": "astroport",
      "change_24h_pct": 1.9354838709677438,
      "change_7d_pct": -1.250000000000001
    },
    "ETH": {
      "price_usd": 1795.37,
      "type": "token",
      "source": "astroport",
      "change_24h_pct": 3.0501139344403363,
      "change_7d_pct": 5.717583187596785
    },
    "WETH": {
      "price_usd": 1795.4007875656937,
      "type": "token",
      "source": "coingecko",
      "change_24h_pct": null,
      "change_7d_pct": null
    },
    "WSTETH": {
      "price_usd": 2223.87,
      "type": "token",
      "source": "astroport",
      "change_24h_pct": 2.9993840054466774,
      "change_7d_pct": 5.882941089648668
    },
    "BNB": {
      "price_usd": 575.41,
      "type": "token",
      "source": "astroport",
      "change_24h_pct": 1.231505427420348,
      "change_7d_pct": 3.1219197476657214
    },
    "WBNB": {
      "price_usd": 575.4368511508038,
      "type": "token",
      "source": "coingecko",
      "change_24h_pct": null,
      "change_7d_pct": null
    },
    "OSMO": {
      "price_usd": 0.03587264300380928,
      "type": "token",
      "source": "coingecko",
      "change_24h_pct": null,
      "change_7d_pct": null
    },
    "STLUNA": {
      "price_usd": 0.08618530248070035,
      "type": "token",
      "source": "coingecko",
      "change_24h_pct": null,
      "change_7d_pct": null
    },
    "STATOM": {
      "price_usd": 3.0375749482312973,
      "type": "token",
      "source": "coingecko",
      "change_24h_pct": null,
      "change_7d_pct": null
    },
    "SOLID": {
      "price_usd": 1.0164868614265044,
      "type": "token",
      "source": "astroport",
      "change_24h_pct": 0.0021147359895911325,
      "change_7d_pct": 0.8438361649065673
    },
    "SWTH": {
      "price_usd": 0.000270431108628389,
      "type": "token",
      "source": "coingecko",
      "change_24h_pct": null,
      "change_7d_pct": null
    },
    "ROAR": {
      "price_usd": 2.04338302868e-7,
      "type": "token",
      "source": "astroport",
      "change_24h_pct": 2.6332968286521132,
      "change_7d_pct": 2.9376680926861067
    },
    "CAPA": {
      "price_usd": 0.001111616840787579,
      "type": "token",
      "source": "astroport",
      "change_24h_pct": 3.1225420750584187,
      "change_7d_pct": 4.321862024170932
    },
    "ASTRO": {
      "price_usd": 0.000302472535627913,
      "type": "token",
      "source": "astroport",
      "change_24h_pct": -0.21487118112969214,
      "change_7d_pct": 15.0409700220353
    },
    "xASTRO": {
      "price_usd": 0.000399048615480471,
      "type": "token",
      "source": "astroport-direct",
      "change_24h_pct": null,
      "change_7d_pct": null
    },
    "ampLUNA": {
      "price_usd": 0.10779260491066275,
      "type": "token",
      "source": "calculated-eris",
      "change_24h_pct": null,
      "change_7d_pct": null
    },
    "arbLUNA": {
      "price_usd": 0.14549916807112484,
      "type": "token",
      "source": "calculated-eris",
      "change_24h_pct": null,
      "change_7d_pct": null
    },
    "bLUNA": {
      "price_usd": 0.08635564893877236,
      "type": "token",
      "source": "calculated-eris",
      "change_24h_pct": null,
      "change_7d_pct": null
    },
    "ampCAPA": {
      "price_usd": 0.0012289343727589848,
      "type": "token",
      "source": "calculated-eris",
      "change_24h_pct": null,
      "change_7d_pct": null
    },
    "ampROAR": {
      "price_usd": 2.407479371468527e-7,
      "type": "token",
      "source": "calculated-eris",
      "change_24h_pct": null,
      "change_7d_pct": null
    }
  },
  "ratios": {
    "ampLUNA": {
      "ratio": 2.2092338148822552,
      "hub": "terra10788fkzah89xrdm27zkj5yvhj9x3494lxawzm5qq3vvxcqz2yzaqyd3enk",
      "base_token": "LUNA",
      "source": "eris-hub-chain"
    },
    "arbLUNA": {
      "ratio": 2.982038354174413,
      "hub": "terra1r9gls56glvuc4jedsvc3uwh6vj95mqm9efc7hnweqxa2nlme5cyqxygy5m",
      "base_token": "LUNA",
      "source": "eris-hub-chain"
    },
    "ampROAR": {
      "ratio": 1.1781831099104942,
      "hub": "terra1vklefn7n6cchn0u962w3gaszr4vf52wjvd4y95t2sydwpmpdtszsqvk9wy",
      "base_token": "ROAR",
      "source": "eris-hub-chain"
    },
    "ampCAPA": {
      "ratio": 1.105537742562704,
      "hub": "terra186rpfczl7l2kugdsqqedegl4es4hp624phfc7ddy8my02a4e8lgq5rlx7y",
      "base_token": "CAPA",
      "source": "eris-hub-chain"
    },
    "bLUNA": {
      "ratio": 1.7698785542825772,
      "hub": "terra1l2nd99yze5fszmhl5svyh5fky9wm4nz4etlgnztfu4e8809gd52q04n3ea",
      "base_token": "LUNA",
      "source": "eris-hub-chain"
    },
    "xASTRO": {
      "ratio": 1.3175473786267706,
      "base_token": "ASTRO",
      "source": "astroport-trpc"
    }
  }
}