{
  "meta": {
    "version": "prices-1.0.0",
    "schemaVersion": 1,
    "generated_at": "2026-07-19T22:00:23.383Z",
    "epoch": 194,
    "source": "network-and-prices (consolidated)",
    "token_count": 27
  },
  "prices": {
    "LUNA": {
      "price_usd": 0.04575428,
      "type": "token",
      "source": "astroport",
      "change_24h_pct": -0.5362713003660592,
      "change_7d_pct": -6.164007100925675
    },
    "USDC": {
      "price_usd": 0.999819,
      "type": "token",
      "source": "astroport",
      "change_24h_pct": -0.007700800883291237,
      "change_7d_pct": 0.0033007063511652254
    },
    "USDT": {
      "price_usd": 0.999209,
      "type": "token",
      "source": "astroport",
      "change_24h_pct": -0.012908545457086064,
      "change_7d_pct": -0.009606676640263483
    },
    "WBTC": {
      "price_usd": 64331,
      "type": "token",
      "source": "astroport",
      "change_24h_pct": 0.6067904227202352,
      "change_7d_pct": 0.9018759018759018
    },
    "PAXG": {
      "price_usd": 4005.05,
      "type": "token",
      "source": "astroport",
      "change_24h_pct": 0.035967539295786916,
      "change_7d_pct": -2.3101352274279474
    },
    "EURE": {
      "price_usd": 1.14,
      "type": "token",
      "source": "astroport",
      "change_24h_pct": 0,
      "change_7d_pct": 0
    },
    "INJ": {
      "price_usd": 5.122258455335921,
      "type": "token",
      "source": "coingecko",
      "change_24h_pct": null,
      "change_7d_pct": null
    },
    "ATOM": {
      "price_usd": 1.48,
      "type": "token",
      "source": "astroport",
      "change_24h_pct": -1.986754966887419,
      "change_7d_pct": -6.329113924050639
    },
    "ETH": {
      "price_usd": 1861.12,
      "type": "token",
      "source": "astroport",
      "change_24h_pct": 1.1027694179767689,
      "change_7d_pct": 4.141323141832343
    },
    "WETH": {
      "price_usd": 1859.8412601537354,
      "type": "token",
      "source": "coingecko",
      "change_24h_pct": null,
      "change_7d_pct": null
    },
    "WSTETH": {
      "price_usd": 2313.08,
      "type": "token",
      "source": "astroport",
      "change_24h_pct": 1.3970655923829849,
      "change_7d_pct": 4.10931775423308
    },
    "BNB": {
      "price_usd": 568.98,
      "type": "token",
      "source": "astroport",
      "change_24h_pct": 0.2307678757024432,
      "change_7d_pct": -0.9694543555826188
    },
    "WBNB": {
      "price_usd": 568.6100271771843,
      "type": "token",
      "source": "coingecko",
      "change_24h_pct": null,
      "change_7d_pct": null
    },
    "OSMO": {
      "price_usd": 0.03272550978386222,
      "type": "token",
      "source": "coingecko",
      "change_24h_pct": null,
      "change_7d_pct": null
    },
    "STLUNA": {
      "price_usd": 0.08430120844534178,
      "type": "token",
      "source": "coingecko",
      "change_24h_pct": null,
      "change_7d_pct": null
    },
    "STATOM": {
      "price_usd": 2.838792027799726,
      "type": "token",
      "source": "coingecko",
      "change_24h_pct": null,
      "change_7d_pct": null
    },
    "SOLID": {
      "price_usd": 1.016185077058579,
      "type": "token",
      "source": "astroport",
      "change_24h_pct": 0.15068843895212367,
      "change_7d_pct": -0.07489027385050184
    },
    "SWTH": {
      "price_usd": 0.00018377554511742,
      "type": "token",
      "source": "coingecko",
      "change_24h_pct": null,
      "change_7d_pct": null
    },
    "ROAR": {
      "price_usd": 1.96225925329e-7,
      "type": "token",
      "source": "astroport",
      "change_24h_pct": 0.3793583091434072,
      "change_7d_pct": -4.146339774664158
    },
    "CAPA": {
      "price_usd": 0.001081459110513765,
      "type": "token",
      "source": "astroport",
      "change_24h_pct": 0.0280403584914869,
      "change_7d_pct": -3.0554466590583718
    },
    "ASTRO": {
      "price_usd": 0.000218990001494065,
      "type": "token",
      "source": "coingecko (astroport flagged stale)",
      "change_24h_pct": 0,
      "change_7d_pct": -100
    },
    "xASTRO": {
      "price_usd": 0.00037350671154662,
      "type": "token",
      "source": "astroport",
      "change_24h_pct": 0,
      "change_7d_pct": -100
    },
    "ampLUNA": {
      "price_usd": 0.10173710141285078,
      "type": "token",
      "source": "calculated-eris",
      "change_24h_pct": null,
      "change_7d_pct": null
    },
    "arbLUNA": {
      "price_usd": 0.13664378066244243,
      "type": "token",
      "source": "calculated-eris",
      "change_24h_pct": null,
      "change_7d_pct": null
    },
    "bLUNA": {
      "price_usd": 0.08097951893887341,
      "type": "token",
      "source": "calculated-eris",
      "change_24h_pct": null,
      "change_7d_pct": null
    },
    "ampCAPA": {
      "price_usd": 0.0011955938637114153,
      "type": "token",
      "source": "calculated-eris",
      "change_24h_pct": null,
      "change_7d_pct": null
    },
    "ampROAR": {
      "price_usd": 2.3162514120554368e-7,
      "type": "token",
      "source": "calculated-eris",
      "change_24h_pct": null,
      "change_7d_pct": null
    }
  },
  "ratios": {
    "ampLUNA": {
      "ratio": 2.2235537618087484,
      "hub": "terra10788fkzah89xrdm27zkj5yvhj9x3494lxawzm5qq3vvxcqz2yzaqyd3enk",
      "base_token": "LUNA",
      "source": "eris-hub-chain"
    },
    "arbLUNA": {
      "ratio": 2.9864699141248083,
      "hub": "terra1r9gls56glvuc4jedsvc3uwh6vj95mqm9efc7hnweqxa2nlme5cyqxygy5m",
      "base_token": "LUNA",
      "source": "eris-hub-chain"
    },
    "ampROAR": {
      "ratio": 1.1804003004047094,
      "hub": "terra1vklefn7n6cchn0u962w3gaszr4vf52wjvd4y95t2sydwpmpdtszsqvk9wy",
      "base_token": "ROAR",
      "source": "eris-hub-chain"
    },
    "ampCAPA": {
      "ratio": 1.1055377425628499,
      "hub": "terra186rpfczl7l2kugdsqqedegl4es4hp624phfc7ddy8my02a4e8lgq5rlx7y",
      "base_token": "CAPA",
      "source": "eris-hub-chain"
    },
    "bLUNA": {
      "ratio": 1.7698785542876734,
      "hub": "terra1l2nd99yze5fszmhl5svyh5fky9wm4nz4etlgnztfu4e8809gd52q04n3ea",
      "base_token": "LUNA",
      "source": "eris-hub-chain"
    },
    "xASTRO": {
      "ratio": null,
      "base_token": "ASTRO",
      "source": "astroport-trpc"
    }
  }
}